[
	{
		"id": 1,
		"title": "Zapatos Caros",
		"description": "Lorem Ipsum",
		"price": 5000,
		"thumbnail": "no hay",
		"code": 123420,
		"stock": 500
	},
	{
		"id": 2,
		"title": "Zapatos Caros",
		"description": "Lorem Ipsum",
		"price": 5000,
		"thumbnail": "no hay",
		"code": 123420,
		"stock": 500
	},
	{
		"id": 3,
		"title": "Zapatos Caros",
		"description": "Lorem Ipsum",
		"price": 5000,
		"thumbnail": "no hay",
		"code": 123420,
		"stock": 500
	},
	{
		"id": 4,
		"title": "Zapatos Caros",
		"description": "Lorem Ipsum",
		"price": 5000,
		"thumbnail": "no hay",
		"code": 123420,
		"stock": 500
	},
	{
		"id": 5,
		"title": "Zapatos Caros",
		"description": "Lorem Ipsum",
		"price": 5000,
		"thumbnail": "no hay",
		"code": 123420,
		"stock": 500
	},
	{
		"id": 6,
		"title": "Zapatos Caros",
		"description": "Lorem Ipsum",
		"price": 5000,
		"thumbnail": "no hay",
		"code": 123420,
		"stock": 500
	},
	{
		"id": 7,
		"title": "Zapatos Caros",
		"description": "Lorem Ipsum",
		"price": 5000,
		"thumbnail": "no hay",
		"code": 123420,
		"stock": 500
	},
	{
		"id": 8,
		"title": "Zapatos Caros",
		"description": "Lorem Ipsum",
		"price": 5000,
		"thumbnail": "no hay",
		"code": 123420,
		"stock": 500
	}
]